ml4chem/__init__.py
ml4chem/metrics.py
ml4chem/utils.py
ml4chem/visualization.py
ml4chem/atomistic/__init__.py
ml4chem/atomistic/potentials.py
ml4chem/atomistic/features/__init__.py
ml4chem/atomistic/features/autoencoders.py
ml4chem/atomistic/features/base.py
ml4chem/atomistic/features/cartesian.py
ml4chem/atomistic/features/coulombmatrix.py
ml4chem/atomistic/features/cutoff.py
ml4chem/atomistic/features/gaussian.py
ml4chem/atomistic/models/__init__.py
ml4chem/atomistic/models/autoencoders.py
ml4chem/atomistic/models/base.py
ml4chem/atomistic/models/gaussian_process.py
ml4chem/atomistic/models/kernelridge.py
ml4chem/atomistic/models/loss.py
ml4chem/atomistic/models/merger.py
ml4chem/atomistic/models/neuralnetwork.py
ml4chem/atomistic/models/se3net.py
ml4chem/backends/__init__.py
ml4chem/backends/available.py
ml4chem/backends/operations.py
ml4chem/data/__init__.py
ml4chem/data/handler.py
ml4chem/data/parser.py
ml4chem/data/preprocessing.py
ml4chem/data/serialization.py
ml4chem/data/utils.py
ml4chem/optim/LBFGS.py
ml4chem/optim/__init__.py
ml4chem/optim/handler.py
ml4chem-0.0.9.data/data/LICENSE
ml4chem-0.0.9.data/scripts/ml4chem
ml4chem-0.0.9.dist-info/LICENSE
ml4chem-0.0.9.dist-info/METADATA
ml4chem-0.0.9.dist-info/WHEEL
ml4chem-0.0.9.dist-info/top_level.txt
ml4chem-0.0.9.dist-info/RECORD
