Metadata-Version: 2.1
Name: ml4chem
Version: 0.0.9
Summary: Machine learning for chemistry and materials.
Home-page: https://github.com/muammar/ml4chem
Author: Muammar El Khatib
Author-email: muammarelkhatib@gmail.com
License: UNKNOWN
Platform: UNKNOWN
Classifier: Programming Language :: Python :: 3
Classifier: Operating System :: OS Independent
Requires-Dist: joblib
Requires-Dist: seaborn
Requires-Dist: dask-ml
Requires-Dist: ase
Requires-Dist: scipy
Requires-Dist: torch
Requires-Dist: numpy
Requires-Dist: pip
Requires-Dist: pandas
Requires-Dist: plotly
Requires-Dist: pytest
Requires-Dist: msgpack-numpy
Requires-Dist: matplotlib
Requires-Dist: dscribe
Requires-Dist: msgpack-python
Requires-Dist: scikit-learn
